{"count":7,"solutions":[{"uid":589916,"name":"August_Light","slogan":"SH | 初二升初三 | 好好玩个游戏算个锤子信息熵啊！","badge":null,"isAdmin":false,"isBanned":false,"color":"Red","ccfLevel":0,"background":"https://cdn.luogu.com.cn/upload/image_hosting/ogal1nb9.png"},{"uid":434929,"name":"Usada_Pekora","slogan":"相逢是问候","badge":null,"isAdmin":false,"isBanned":false,"color":"Red","ccfLevel":7,"background":""},{"uid":993404,"name":"harmis_yz","slogan":"蓝以上壶关|AT你【】【】了","badge":null,"isAdmin":false,"isBanned":false,"color":"Red","ccfLevel":0,"background":"https://cdn.luogu.com.cn/upload/image_hosting/usmwb3tk.png"},{"uid":706523,"name":"zhengdongwen","slogan":"激情，创造！！！","badge":null,"isAdmin":false,"isBanned":false,"color":"Red","ccfLevel":0,"background":"https://cdn.luogu.com.cn/upload/image_hosting/mvf4w55f.png"},{"uid":624064,"name":"syxmz","slogan":"OI 一旦和功利沾上了边，就没那么可爱了","badge":null,"isAdmin":false,"isBanned":false,"color":"Orange","ccfLevel":5,"background":""},{"uid":460457,"name":"KnownError_","slogan":"SH OIer | 大沙币 | 我们遭遇了亿些技术问题","badge":null,"isAdmin":false,"isBanned":false,"color":"Red","ccfLevel":4,"background":"https://cdn.luogu.com.cn/upload/image_hosting/zb41etcx.png"},{"uid":714821,"name":"loser_seele","slogan":"大局已定。","badge":null,"isAdmin":false,"isBanned":false,"color":"Red","ccfLevel":4,"background":"https://cdn.luogu.com.cn/upload/image_hosting/nieg4cw7.png"}]}