{"count":8,"solutions":[{"uid":578029,"name":"ivyjiao","slogan":"Periodically releases radiation in a large radius. Causes even the most passive mobs to become very aggressive.","badge":null,"isAdmin":false,"isBanned":false,"color":"Red","ccfLevel":3,"background":"https://cdn.luogu.com.cn/upload/image_hosting/o77lj401.png"},{"uid":763542,"name":"jasonsuri1424","slogan":"","badge":null,"isAdmin":false,"isBanned":false,"color":"Red","ccfLevel":0,"background":""},{"uid":363036,"name":"chlchl","slogan":"今年，我看着自己的五级勾，看着 vp 的 NOIp 超过 7 级的分数线，再也忍不住流泪 | 我怎么这么菜啊 QAQ","badge":null,"isAdmin":false,"isBanned":false,"color":"Red","ccfLevel":5,"background":"https://cdn.luogu.com.cn/upload/image_hosting/0r3hhvlh.png"},{"uid":463956,"name":"incra","slogan":"你不需要很厉害才能开始，但你需要开始才会很厉害","badge":null,"isAdmin":false,"isBanned":false,"color":"Red","ccfLevel":5,"background":""},{"uid":359270,"name":"是青白呀","slogan":"应承认差距，找自身问题","badge":null,"isAdmin":false,"isBanned":false,"color":"Orange","ccfLevel":5,"background":"https://cdn.luogu.com.cn/upload/image_hosting/emx4gwze.png"},{"uid":775213,"name":"yangmingshuo114514","slogan":"","badge":null,"isAdmin":false,"isBanned":false,"color":"Red","ccfLevel":0,"background":""},{"uid":295398,"name":"1105Lee","slogan":"Go big or go home","badge":null,"isAdmin":false,"isBanned":false,"color":"Red","ccfLevel":0,"background":"https://cdn.luogu.com.cn/upload/image_hosting/39ccq8qz.png"},{"uid":637796,"name":"Xy_top","slogan":"一个可爱的小沙币","badge":null,"isAdmin":false,"isBanned":false,"color":"Red","ccfLevel":0,"background":""}]}