{"count":9,"solutions":[{"uid":251551,"name":"YUYGFGG","slogan":"AFO","badge":null,"isAdmin":false,"isBanned":false,"color":"Green","ccfLevel":4,"background":""},{"uid":304524,"name":"崔化博","slogan":"有绿勾了","badge":null,"isAdmin":false,"isBanned":false,"color":"Red","ccfLevel":5,"background":"https://cdn.luogu.com.cn/upload/image_hosting/65fsg66b.png"},{"uid":304504,"name":"蓝__","slogan":"愿此行，终抵群星","badge":null,"isAdmin":false,"isBanned":false,"color":"Orange","ccfLevel":5,"background":"https://cdn.luogu.com.cn/upload/image_hosting/fpc1f6zb.png"},{"uid":384035,"name":"Mysterious_Cat","slogan":"天道酬勤","badge":null,"isAdmin":false,"isBanned":false,"color":"Red","ccfLevel":7,"background":""},{"uid":358815,"name":"落河之秋","slogan":"我仍然在 无人问津的阴雨霉湿之地 和着雨音 唱着没有听众的歌曲","badge":null,"isAdmin":false,"isBanned":false,"color":"Gray","ccfLevel":0,"background":"https://cdn.luogu.com.cn/upload/image_hosting/y0obljk8.png"},{"uid":303132,"name":"Okimoto_Liar","slogan":"  ","badge":null,"isAdmin":false,"isBanned":false,"color":"Orange","ccfLevel":0,"background":"https://cdn.luogu.com.cn/upload/image_hosting/x86o9zaw.png"},{"uid":413301,"name":"Digital_Sunrise","slogan":"","badge":null,"isAdmin":false,"isBanned":false,"color":"Orange","ccfLevel":7,"background":"https://cdn.luogu.com.cn/upload/image_hosting/c4dnh86z.png"},{"uid":162084,"name":"thomas_zjl","slogan":"3423234307","badge":null,"isAdmin":false,"isBanned":false,"color":"Red","ccfLevel":4,"background":"https://cdn.luogu.com.cn/upload/image_hosting/cpxwe6uj.png"},{"uid":112917,"name":"Eason_AC","slogan":"「さよなら世界 私の夢にまで見た世界」/ AFOed on 2022.6.14","badge":null,"isAdmin":false,"isBanned":false,"color":"Red","ccfLevel":6,"background":"https://cdn.luogu.com.cn/upload/image_hosting/u6qol99b.png"}]}