{"count":5,"solutions":[{"uid":694118,"name":"shaozhehan","slogan":"关注必互关||一只小菜鸟呵呵了⎛⎝≥⏝⏝≤⎛⎝ฏ๎๎๎๎๎๎๎๎๎๎๎๎๎๎๎๎๎๎๎๎๎๎๎๎๎๎๎๎๎๎๎๎๎๎๎๎๎๎๎๎๎๎๎๎๎๎๎๎๎๎๎๎๎๎๎๎๎๎๎๎๎๎๎๎๎๎||支持送出SPOJ与UVA账号（私信用户名、密码、邮箱、验证码）","badge":null,"isAdmin":false,"isBanned":false,"color":"Red","ccfLevel":4,"background":""},{"uid":541145,"name":"Fleeing_loser","slogan":"lovely","badge":null,"isAdmin":false,"isBanned":false,"color":"Red","ccfLevel":0,"background":"https://cdn.luogu.com.cn/upload/image_hosting/0sa7isam.png"},{"uid":593613,"name":"olegekei","slogan":"这下真的AFO了。","badge":null,"isAdmin":false,"isBanned":false,"color":"Red","ccfLevel":7,"background":"https://cdn.luogu.com.cn/upload/image_hosting/lu6cswgi.png"},{"uid":127949,"name":"cmk666","slogan":"⎛⎝≥⏝⏝≤⎠⎞ | 拳击房最菜 | /duel decline | 毫无实力 | 我是智利障碍 | 伊娜可爱捏 伊娜贴贴捏","badge":null,"isAdmin":false,"isBanned":false,"color":"Red","ccfLevel":7,"background":"https://cdn.luogu.com.cn/upload/image_hosting/xbxnaw32.png"},{"uid":397282,"name":"_NTT_","slogan":"document.body.contentEditable='true';","badge":null,"isAdmin":false,"isBanned":false,"color":"Red","ccfLevel":5,"background":"https://cdn.luogu.com.cn/upload/image_hosting/ytmjrhuw.png"}]}