{"count":4,"solutions":[{"uid":15263,"name":"cyp0633","slogan":"早已退役的SE生。","badge":null,"isAdmin":false,"isBanned":false,"color":"Green","ccfLevel":3,"background":""},{"uid":65799,"name":"快乐的坤","slogan":"红题真好吃","badge":null,"isAdmin":false,"isBanned":false,"color":"Gray","ccfLevel":0,"background":""},{"uid":78585,"name":"Silencedied","slogan":"","badge":null,"isAdmin":false,"isBanned":false,"color":"Gray","ccfLevel":0,"background":""},{"uid":280679,"name":"miaohongxuan","slogan":"祖国在我心","badge":null,"isAdmin":false,"isBanned":false,"color":"Green","ccfLevel":0,"background":"https://cdn.luogu.com.cn/upload/image_hosting/ceyhgbbl.png"}]}