{"count":12,"solutions":[{"uid":254315,"name":"Larry76","slogan":"一笔一画，两世三生，念言温玉，十指芳缘","badge":null,"isAdmin":false,"isBanned":false,"color":"Orange","ccfLevel":0,"background":"https://cdn.luogu.com.cn/upload/image_hosting/t2xerhno.png"},{"uid":54544,"name":"LJB00131","slogan":"","badge":null,"isAdmin":false,"isBanned":false,"color":"Gray","ccfLevel":7,"background":""},{"uid":54900,"name":"__Hacheylight__","slogan":"AFO","badge":null,"isAdmin":false,"isBanned":false,"color":"Gray","ccfLevel":0,"background":"https://cdn.luogu.com.cn/upload/image_hosting/7mt1ft5w.png"},{"uid":592238,"name":"__dest__ruct__or__","slogan":"你谷最蒻红名||六年级 xxs，不再壶关||OI 和 whk 都很菜，无数次被吊打和单调队列还搁这硬撑的屑。||没有钩子不删","badge":null,"isAdmin":false,"isBanned":false,"color":"Red","ccfLevel":0,"background":"https://cdn.luogu.com.cn/upload/image_hosting/m3g6wtsn.png"},{"uid":561536,"name":"JEB_him","slogan":"While(True) Love;","badge":null,"isAdmin":false,"isBanned":false,"color":"Blue","ccfLevel":0,"background":"https://cdn.luogu.com.cn/upload/image_hosting/nmfrp4vg.png"},{"uid":453100,"name":"Tzs_yousa","slogan":"南风知我意，吹梦到西洲。","badge":null,"isAdmin":false,"isBanned":false,"color":"Orange","ccfLevel":4,"background":"https://cdn.luogu.com.cn/upload/image_hosting/l0o6vl8f.png"},{"uid":488775,"name":"_SAI_","slogan":"ㅤ","badge":null,"isAdmin":false,"isBanned":false,"color":"Orange","ccfLevel":5,"background":"https://cdn.luogu.com.cn/upload/image_hosting/7ht80mpi.png"},{"uid":456787,"name":"lightningZ","slogan":"贪心万岁！世界是由贪心构成的！||不定期查互关||322417","badge":null,"isAdmin":false,"isBanned":false,"color":"Blue","ccfLevel":0,"background":"https://cdn.luogu.com.cn/upload/image_hosting/6r7zo4c8.png"},{"uid":212283,"name":"Aw顿顿","slogan":"长日尽处，我来到你的面前，你将看见我的伤痕，你会知晓我曾受伤，也曾痊愈","badge":null,"isAdmin":false,"isBanned":false,"color":"Green","ccfLevel":5,"background":"https://cdn.luogu.com.cn/upload/image_hosting/1uw27wzq.png"},{"uid":132168,"name":"_Clown_","slogan":"AFOed","badge":null,"isAdmin":false,"isBanned":false,"color":"Orange","ccfLevel":6,"background":""},{"uid":277023,"name":"YuanZhizheng","slogan":"先把字符串相关算法搞完吧","badge":null,"isAdmin":false,"isBanned":false,"color":"Blue","ccfLevel":0,"background":"https://cdn.luogu.com.cn/upload/image_hosting/k050znbp.png"},{"uid":61015,"name":"玉环小姐姐","slogan":"祥瑞御免，家宅平安","badge":null,"isAdmin":false,"isBanned":false,"color":"Green","ccfLevel":5,"background":""}]}