{"count":10,"solutions":[{"uid":719577,"name":"wanguan","slogan":"真寻酱卡哇伊||有原则壶关，见主页","badge":null,"isAdmin":false,"isBanned":false,"color":"Orange","ccfLevel":0,"background":"https://cdn.luogu.com.cn/upload/image_hosting/yau32biq.png"},{"uid":372119,"name":"DynamicProb","slogan":"I like dynamic programming（）","badge":null,"isAdmin":false,"isBanned":false,"color":"Green","ccfLevel":4,"background":"https://cdn.luogu.com.cn/upload/image_hosting/cjyddd07.png"},{"uid":474692,"name":"csy114514","slogan":"这个家伙不懒，但什么也没有留下","badge":null,"isAdmin":false,"isBanned":false,"color":"Orange","ccfLevel":3,"background":""},{"uid":648568,"name":"lmz_","slogan":"","badge":null,"isAdmin":false,"isBanned":false,"color":"Blue","ccfLevel":0,"background":"https://cdn.luogu.com.cn/upload/image_hosting/68wm81q4.png"},{"uid":649435,"name":"songaiwu","slogan":"此生不悔入华夏，来世仍做种花兔ด้้้้้็้้้็็็็็้้้้้็็็็็้้้้้้็็็็็้้้้้็็็็็้้้้้้็็็็็้้้้้็็็็็้้้้้้็็็็็้้้้้็็็็็้้้้้้็","badge":null,"isAdmin":false,"isBanned":false,"color":"Orange","ccfLevel":5,"background":"https://cdn.luogu.com.cn/upload/image_hosting/7tf2pgju.png"},{"uid":719939,"name":"a12a","slogan":"优先 whk，搞好再 OI，追求利益最大化！|| 逸一时,误一世,逸久逸久罢己龄","badge":null,"isAdmin":false,"isBanned":false,"color":"Orange","ccfLevel":0,"background":"https://cdn.luogu.com.cn/upload/image_hosting/fq3jwp7g.png"},{"uid":535904,"name":"_lmz_","slogan":"AFO~","badge":null,"isAdmin":false,"isBanned":false,"color":"Gray","ccfLevel":0,"background":"https://cdn.luogu.com.cn/upload/image_hosting/s3c5a60u.png"},{"uid":474522,"name":"Anduin_Urien","slogan":"That I should never reveal the bset for you ? When you risk your life every day to portect the boy?","badge":null,"isAdmin":false,"isBanned":false,"color":"Green","ccfLevel":4,"background":"https://cdn.luogu.com.cn/upload/image_hosting/c5knmqks.png"},{"uid":279197,"name":"Mars_Dingdang","slogan":"最怕你一生碌碌无为，却总安慰自己平凡可贵","badge":null,"isAdmin":false,"isBanned":false,"color":"Red","ccfLevel":8,"background":"https://cdn.luogu.com.cn/upload/image_hosting/t2nd97ds.png"},{"uid":100910,"name":"⚡小林子⚡","slogan":"没退役垃圾whk人","badge":null,"isAdmin":false,"isBanned":false,"color":"Orange","ccfLevel":7,"background":"https://cdn.luogu.com.cn/upload/image_hosting/wrqpygsk.png"}]}