{"count":8,"solutions":[{"uid":254752,"name":"JohnVictor","slogan":"云OIer","badge":"云 OIer","isAdmin":true,"isBanned":false,"color":"Purple","ccfLevel":6,"background":""},{"uid":678877,"name":"Pengzt","slogan":"I will do it.","badge":null,"isAdmin":false,"isBanned":false,"color":"Red","ccfLevel":0,"background":""},{"uid":670775,"name":"12345678hzx","slogan":"六年级|绿钩|红名|蒟蒻|黄梅时节家家雨，青草池塘处处 WA","badge":null,"isAdmin":false,"isBanned":false,"color":"Red","ccfLevel":4,"background":"https://cdn.luogu.com.cn/upload/image_hosting/5q69s72y.png"},{"uid":526017,"name":"The_cosmos","slogan":"知耻而后勇。","badge":null,"isAdmin":false,"isBanned":false,"color":"Red","ccfLevel":4,"background":"https://cdn.luogu.com.cn/upload/image_hosting/8f7wmau3.png"},{"uid":560516,"name":"喵仔牛奶","slogan":"所以我大师，他是小丑。","badge":null,"isAdmin":false,"isBanned":false,"color":"Red","ccfLevel":0,"background":"https://cdn.luogu.com.cn/upload/image_hosting/gt7z598c.png"},{"uid":760824,"name":"MornStar","slogan":"初一点五旺仔蒟蒻果冻","badge":null,"isAdmin":false,"isBanned":false,"color":"Red","ccfLevel":0,"background":"https://cdn.luogu.com.cn/upload/image_hosting/0wzs18nu.png"},{"uid":336603,"name":"出言不逊王子","slogan":"喜欢养狗，不爱洗头","badge":null,"isAdmin":false,"isBanned":false,"color":"Red","ccfLevel":0,"background":""},{"uid":593613,"name":"olegekei","slogan":"这下真的AFO了。","badge":null,"isAdmin":false,"isBanned":false,"color":"Red","ccfLevel":7,"background":"https://cdn.luogu.com.cn/upload/image_hosting/lu6cswgi.png"}]}