{"count":10,"solutions":[{"uid":229170,"name":"Zhoumy","slogan":"AFO&&既然选择了远方,便只顾风雨兼程&&世界上最水的c++游戏们的开发者","badge":null,"isAdmin":false,"isBanned":false,"color":"Green","ccfLevel":5,"background":"https://cdn.luogu.com.cn/upload/image_hosting/pqb6wch3.png"},{"uid":468175,"name":"_xbn","slogan":"今天这个地区是晴天，昨天我一整天都很享受","badge":null,"isAdmin":false,"isBanned":false,"color":"Gray","ccfLevel":0,"background":"https://cdn.luogu.com.cn/upload/image_hosting/6k79w2h5.png"},{"uid":147999,"name":"Warriors_Cat","slogan":"欢迎来到这方净土，这里曾有一位普通人建造着自己的乌托邦。","badge":null,"isAdmin":false,"isBanned":false,"color":"Red","ccfLevel":7,"background":"https://cdn.luogu.com.cn/upload/image_hosting/o5wcrxqx.png"},{"uid":526519,"name":"Aisaka_Taiga","slogan":"我们的心就像那天空一样，永不分离。—— 缘之空","badge":null,"isAdmin":false,"isBanned":false,"color":"Red","ccfLevel":0,"background":"https://cdn.luogu.com.cn/upload/image_hosting/3xp1nzjd.png"},{"uid":302103,"name":"lu_fish","slogan":"[]","badge":null,"isAdmin":false,"isBanned":false,"color":"Red","ccfLevel":6,"background":""},{"uid":250699,"name":"Herkaii","slogan":"","badge":null,"isAdmin":false,"isBanned":false,"color":"Green","ccfLevel":4,"background":""},{"uid":240812,"name":"45dino","slogan":"不要停下来啊>_<","badge":null,"isAdmin":false,"isBanned":false,"color":"Green","ccfLevel":0,"background":""},{"uid":305891,"name":"Warp","slogan":"","badge":null,"isAdmin":false,"isBanned":false,"color":"Red","ccfLevel":5,"background":"https://cdn.luogu.com.cn/upload/image_hosting/auym5w3i.png"},{"uid":314337,"name":"cherish_","slogan":"没有AC不了的题，只有不努力的ACMER！","badge":null,"isAdmin":false,"isBanned":false,"color":"Gray","ccfLevel":0,"background":"https://cdn.luogu.com.cn/upload/image_hosting/dz6jegrm.png"},{"uid":122461,"name":"rui_er","slogan":"尺子姐姐可爱捏~","badge":null,"isAdmin":false,"isBanned":false,"color":"Red","ccfLevel":7,"background":"https://cdn.luogu.com.cn/upload/image_hosting/ezmx3njc.png"}]}