{"count":15,"solutions":[{"uid":60489,"name":"小菜鸟","slogan":"咕咕咕（","badge":null,"isAdmin":false,"isBanned":false,"color":"Orange","ccfLevel":7,"background":"https://cdn.luogu.com.cn/upload/image_hosting/om1iaovp.png"},{"uid":153123,"name":"AK_Dream","slogan":"菜的没边","badge":null,"isAdmin":false,"isBanned":false,"color":"Orange","ccfLevel":9,"background":"https://cdn.luogu.com.cn/upload/image_hosting/bc1yuysj.png"},{"uid":123294,"name":"Alex_Wei","slogan":"Here we go again!","badge":"","isAdmin":false,"isBanned":false,"color":"Red","ccfLevel":10,"background":""},{"uid":129578,"name":"Calculatelove","slogan":"所以暂时将你眼睛闭了起来~","badge":null,"isAdmin":false,"isBanned":false,"color":"Gray","ccfLevel":7,"background":""},{"uid":330759,"name":"囧仙","slogan":"你做东方鬼畜音MAD，好吗？","badge":null,"isAdmin":false,"isBanned":false,"color":"Gray","ccfLevel":0,"background":""},{"uid":111728,"name":"幻影星坚强","slogan":"この世で造花より綺麗な花は無いわ 何故ならば総ては嘘で出来ている","badge":null,"isAdmin":false,"isBanned":false,"color":"Red","ccfLevel":7,"background":"https://cdn.luogu.com.cn/upload/image_hosting/kqzd98nk.png"},{"uid":54357,"name":"OMG_wc","slogan":"","badge":null,"isAdmin":false,"isBanned":false,"color":"Orange","ccfLevel":0,"background":""},{"uid":61580,"name":"little_prince","slogan":"但行好事，莫问前程。","badge":null,"isAdmin":false,"isBanned":false,"color":"Blue","ccfLevel":0,"background":""},{"uid":68561,"name":"clockwhite","slogan":"失去的都是已知的，得到的都是未知的","badge":null,"isAdmin":false,"isBanned":false,"color":"Gray","ccfLevel":0,"background":"https://cdn.luogu.com.cn/upload/image_hosting/31pt8iiq.png"},{"uid":73551,"name":"zjjws","slogan":"Dirty Deeds Done Dirt Cheap","badge":null,"isAdmin":false,"isBanned":false,"color":"Red","ccfLevel":7,"background":"https://cdn.luogu.com.cn/upload/image_hosting/2m0we87c.png"},{"uid":237308,"name":"AlanSP","slogan":"僕は新世界の神となる！","badge":null,"isAdmin":false,"isBanned":false,"color":"Green","ccfLevel":0,"background":"https://cdn.luogu.com.cn/upload/image_hosting/tifzh4uk.png"},{"uid":71936,"name":"HoshiuZ","slogan":"生命潦草，我在弯腰。","badge":null,"isAdmin":false,"isBanned":false,"color":"Orange","ccfLevel":6,"background":""},{"uid":31488,"name":"wenhao801","slogan":"BlaBloBliBloooo!!!","badge":null,"isAdmin":false,"isBanned":false,"color":"Red","ccfLevel":9,"background":"https://cdn.luogu.com.cn/upload/image_hosting/uowrh6eo.png"},{"uid":24425,"name":"fysbb","slogan":"That's♂good!","badge":null,"isAdmin":false,"isBanned":false,"color":"Green","ccfLevel":6,"background":""},{"uid":105254,"name":"Piwry","slogan":"一人だけの旅々","badge":null,"isAdmin":false,"isBanned":false,"color":"Gray","ccfLevel":7,"background":"https://cdn.luogu.com.cn/upload/image_hosting/qudyjykh.png"}]}