{"count":6,"solutions":[{"uid":47757,"name":"dunko","slogan":"仰望前方","badge":null,"isAdmin":false,"isBanned":false,"color":"Gray","ccfLevel":6,"background":"https://cdn.luogu.com.cn/upload/image_hosting/w0ufjm3k.png"},{"uid":438461,"name":"liu_chen_hao","slogan":"我永远喜欢珂朵莉~","badge":null,"isAdmin":false,"isBanned":false,"color":"Green","ccfLevel":0,"background":"https://cdn.luogu.com.cn/upload/image_hosting/yxph6fzm.png"},{"uid":503899,"name":"_byta","slogan":"little monkey search problem","badge":null,"isAdmin":false,"isBanned":false,"color":"Gray","ccfLevel":0,"background":"https://cdn.luogu.com.cn/upload/image_hosting/kwirys3z.png"},{"uid":156945,"name":"Stream月","slogan":"[AFOed]你们全部变成小鸟的点心(?8?)","badge":null,"isAdmin":false,"isBanned":false,"color":"Green","ccfLevel":6,"background":"https://cdn.luogu.com.cn/upload/image_hosting/gxxd0ct7.png"},{"uid":27924,"name":"xukuan","slogan":"每日一膜hehezhou","badge":null,"isAdmin":false,"isBanned":false,"color":"Blue","ccfLevel":0,"background":""},{"uid":559502,"name":"TsH_GD","slogan":"去清北摘果果","badge":null,"isAdmin":false,"isBanned":false,"color":"Green","ccfLevel":4,"background":"https://cdn.luogu.com.cn/upload/image_hosting/d2a37bnl.png"}]}