{"count":4,"solutions":[{"uid":26127,"name":"Weng_Weijie","slogan":"やー！今日もパンがうまい！","badge":null,"isAdmin":false,"isBanned":false,"color":"Orange","ccfLevel":9,"background":""},{"uid":138400,"name":"chenxia25","slogan":"Всё ж старается не зря...","badge":null,"isAdmin":false,"isBanned":false,"color":"Red","ccfLevel":9,"background":"https://cdn.luogu.com.cn/upload/image_hosting/bunmrzq7.png"},{"uid":201007,"name":"Leasier","slogan":"我们所知的是沧海一粟，我们所不知的是汪洋大海。","badge":null,"isAdmin":false,"isBanned":false,"color":"Red","ccfLevel":8,"background":""},{"uid":335096,"name":"Eznibuil","slogan":"Newbie killed you with their Bayonet.","badge":null,"isAdmin":false,"isBanned":false,"color":"Red","ccfLevel":7,"background":""}]}