{"count":6,"solutions":[{"uid":118318,"name":"ez_lcw","slogan":"","badge":null,"isAdmin":false,"isBanned":false,"color":"Green","ccfLevel":0,"background":"https://cdn.luogu.com.cn/upload/image_hosting/o6gx8n8x.png"},{"uid":106182,"name":"KaisuoShutong","slogan":"我想说别走 却没有借口。","badge":null,"isAdmin":false,"isBanned":false,"color":"Orange","ccfLevel":9,"background":"https://cdn.luogu.com.cn/upload/image_hosting/jbsv7dep.png"},{"uid":343748,"name":"louhao088","slogan":"这个家伙不懒，但还是什么都没留下","badge":null,"isAdmin":false,"isBanned":false,"color":"Red","ccfLevel":9,"background":"https://cdn.luogu.com.cn/upload/image_hosting/miy0v9mi.png"},{"uid":206998,"name":"Krimson","slogan":"别祈祷","badge":null,"isAdmin":false,"isBanned":false,"color":"Orange","ccfLevel":0,"background":"https://cdn.luogu.com.cn/upload/image_hosting/hwerdxye.png"},{"uid":242543,"name":"Ryo_Yamada","slogan":"","badge":null,"isAdmin":false,"isBanned":false,"color":"Red","ccfLevel":7,"background":"https://cdn.luogu.com.cn/upload/image_hosting/rnxtq8c4.png"},{"uid":530186,"name":"YYXgf2009","slogan":"为真爱与梦想，永恒于天穹。","badge":null,"isAdmin":false,"isBanned":false,"color":"Red","ccfLevel":4,"background":"https://cdn.luogu.com.cn/upload/image_hosting/esxsxrym.png"}]}