{"count":9,"solutions":[{"uid":717971,"name":"liuyi0905","slogan":"不AK IOI不改个签||互关忘私⎛⎝≥⏝⏝≤⎛⎝ด้้้้้็้้้็็็็็้้้้้็็็็็้้้้้้็็็็็้้้้้็็็็็้้้้้้็็็็็้้้้้็็็็็้้้้้้็็็็็้้้้้็็็็็้้้้้้็็","badge":null,"isAdmin":false,"isBanned":false,"color":"Red","ccfLevel":0,"background":"https://cdn.luogu.com.cn/upload/image_hosting/ieddta7x.png"},{"uid":482592,"name":"cyfqwq","slogan":"MnZn敲阔奈了喵o((>ω< ))o","badge":null,"isAdmin":false,"isBanned":false,"color":"Red","ccfLevel":4,"background":"https://cdn.luogu.com.cn/upload/image_hosting/jvckrfv6.png"},{"uid":778022,"name":"livedreamyhy","slogan":"一个学了一年 OI 连 Floyd 都不会的蒟蒻","badge":null,"isAdmin":false,"isBanned":false,"color":"Orange","ccfLevel":0,"background":"https://cdn.luogu.com.cn/upload/image_hosting/yz7edt1c.png"},{"uid":800322,"name":"Zouzhuoxuan","slogan":"愿，自己不再辜负自己，奇迹不再辜负奇迹","badge":null,"isAdmin":false,"isBanned":false,"color":"Orange","ccfLevel":0,"background":"https://cdn.luogu.com.cn/upload/image_hosting/ob5xu201.png"},{"uid":785630,"name":"YangXiaopei","slogan":"说句闲话，研究珂学的最好方法      是A了这道题 祝你们成功（滑稽","badge":null,"isAdmin":false,"isBanned":false,"color":"Red","ccfLevel":0,"background":"https://cdn.luogu.com.cn/upload/image_hosting/6kmealmu.png"},{"uid":679961,"name":"zhang_kevin","slogan":"","badge":null,"isAdmin":false,"isBanned":false,"color":"Red","ccfLevel":0,"background":""},{"uid":411727,"name":"stOtue","slogan":"我们所知的是沧海一粟，我们所不知的是汪洋大海。","badge":"","isAdmin":false,"isBanned":false,"color":"Red","ccfLevel":0,"background":""},{"uid":526677,"name":"mzycの喰种","slogan":"蝶飞芳浓，雪霁梅香","badge":null,"isAdmin":false,"isBanned":false,"color":"Red","ccfLevel":0,"background":"https://cdn.luogu.com.cn/upload/image_hosting/tsioau72.png"},{"uid":298208,"name":"BorisDimitri","slogan":"AFOed","badge":null,"isAdmin":false,"isBanned":false,"color":"Green","ccfLevel":5,"background":"https://cdn.luogu.com.cn/upload/image_hosting/s74cvkuc.png"}]}