{"count":7,"solutions":[{"uid":367488,"name":"liangbowen","slogan":"差不多得了。","badge":null,"isAdmin":false,"isBanned":false,"color":"Red","ccfLevel":0,"background":"https://cdn.luogu.com.cn/upload/image_hosting/njfltd6z.png"},{"uid":101694,"name":"yummy","slogan":"这个人是时代的眼泪，什么也没有留下","badge":null,"isAdmin":false,"isBanned":false,"color":"Orange","ccfLevel":7,"background":""},{"uid":305121,"name":"8atemak1r","slogan":"I have been AKed by  CSP、NOIP","badge":null,"isAdmin":false,"isBanned":false,"color":"Orange","ccfLevel":6,"background":"https://cdn.luogu.com.cn/upload/image_hosting/n6yu87pu.png"},{"uid":80679,"name":"Register","slogan":"","badge":null,"isAdmin":false,"isBanned":false,"color":"Red","ccfLevel":9,"background":"https://cdn.luogu.com.cn/upload/image_hosting/xmh9q0oz.png"},{"uid":19729,"name":"xiaohuang","slogan":"There is no good and evil, there is only power and those too weak to seek it.","badge":null,"isAdmin":false,"isBanned":false,"color":"Gray","ccfLevel":5,"background":"https://cdn.luogu.com.cn/upload/image_hosting/ta0ukqcw.png"},{"uid":518232,"name":"dage666","slogan":"不开 long long 见祖宗 | 再压行 AKIOI | 加上模数再取模","badge":null,"isAdmin":false,"isBanned":false,"color":"Orange","ccfLevel":0,"background":"https://cdn.luogu.com.cn/upload/image_hosting/wmsuqlap.png"},{"uid":224558,"name":"JackMerryYoung","slogan":"警惕绿色安顿势力入侵。兴罢了，今天就写到这儿吧。何时才能为所欲为！？这是个 ZJ OIer | Zipoard 绘版交流群 165425819 欢迎来玩","badge":null,"isAdmin":false,"isBanned":false,"color":"Red","ccfLevel":5,"background":"https://cdn.luogu.com.cn/upload/image_hosting/bvmnz7aa.png"}]}