{"count":4,"solutions":[{"uid":158846,"name":"xixike","slogan":"人间忽晚，山河已秋。","badge":null,"isAdmin":false,"isBanned":false,"color":"Orange","ccfLevel":0,"background":"https://cdn.luogu.com.cn/upload/image_hosting/dspv1gba.png"},{"uid":434929,"name":"Usada_Pekora","slogan":"我是小初生","badge":null,"isAdmin":false,"isBanned":false,"color":"Red","ccfLevel":7,"background":""},{"uid":145596,"name":"AquaRio","slogan":"青鸟终将飞越那道彩虹的彼端， 所以我们也一定能够做到。","badge":null,"isAdmin":false,"isBanned":false,"color":"Green","ccfLevel":6,"background":"https://cdn.luogu.com.cn/upload/image_hosting/14xweup5.png"},{"uid":62440,"name":"MuelsyseU","slogan":"行き場のない声の淵か 赤い水が流れ落ちるのら","badge":null,"isAdmin":false,"isBanned":false,"color":"Red","ccfLevel":0,"background":"https://cdn.luogu.com.cn/upload/image_hosting/k1r9562m.png"}]}