{"count":54,"solutions":[{"uid":41707,"name":"zhuwanman","slogan":"","badge":null,"isAdmin":false,"isBanned":false,"color":"Gray","ccfLevel":0,"background":""},{"uid":111197,"name":"lqhsr","slogan":"☝这个家伙很♂，✓什么也没有留↓","badge":null,"isAdmin":false,"isBanned":false,"color":"Blue","ccfLevel":0,"background":"https://cdn.luogu.com.cn/upload/image_hosting/igbqreov.png"},{"uid":18673,"name":"ctq1999","slogan":"今晚はの月が綺麗ですね","badge":null,"isAdmin":false,"isBanned":false,"color":"Green","ccfLevel":6,"background":"https://cdn.luogu.com.cn/upload/image_hosting/izg74sjn.png"},{"uid":65376,"name":"栩笙丶","slogan":"","badge":null,"isAdmin":false,"isBanned":false,"color":"Gray","ccfLevel":0,"background":""},{"uid":22630,"name":"Running_Coder","slogan":"","badge":null,"isAdmin":false,"isBanned":false,"color":"Blue","ccfLevel":0,"background":""},{"uid":72598,"name":"logwzc","slogan":"这个家伙不懒，但还是什么也没有留下","badge":null,"isAdmin":false,"isBanned":false,"color":"Orange","ccfLevel":7,"background":""},{"uid":34530,"name":"子谦。","slogan":"以这个世界为棋盘，来一场最棒的博弈吧","badge":null,"isAdmin":false,"isBanned":false,"color":"Orange","ccfLevel":6,"background":""},{"uid":83903,"name":"靛涟","slogan":"刹那余烬，是曾经鲜活跃动的记忆中铭刻至深的梦。","badge":null,"isAdmin":false,"isBanned":false,"color":"Blue","ccfLevel":0,"background":""},{"uid":126484,"name":"first_fan","slogan":"Just Do It,But Not Just Do It.","badge":null,"isAdmin":false,"isBanned":false,"color":"Blue","ccfLevel":0,"background":"https://cdn.luogu.com.cn/upload/image_hosting/f61stx63.png"},{"uid":2674,"name":"「QQ红包」","slogan":"","badge":"发红包了","isAdmin":true,"isBanned":false,"color":"Purple","ccfLevel":0,"background":""},{"uid":88471,"name":"Lskkkno1","slogan":"It is realy hard to reach the top.","badge":null,"isAdmin":false,"isBanned":false,"color":"Red","ccfLevel":7,"background":"https://cdn.luogu.com.cn/upload/image_hosting/ovb6srzs.png"},{"uid":93292,"name":"离子键Ionic_Bond","slogan":"峣峣者粉身碎骨而活，皎皎者跌落污泽赴火","badge":null,"isAdmin":false,"isBanned":false,"color":"Gray","ccfLevel":5,"background":"https://cdn.luogu.com.cn/upload/image_hosting/34oiouhc.png"},{"uid":28764,"name":"千梦羽翼","slogan":"因为没有翅膀，所以不会飞翔","badge":null,"isAdmin":false,"isBanned":false,"color":"Green","ccfLevel":4,"background":"https://cdn.luogu.com.cn/upload/image_hosting/2g0jzijl.png"},{"uid":32878,"name":"foreverlasting","slogan":"果然，失去别人远比自己离去更加令人恐惧。","badge":null,"isAdmin":false,"isBanned":false,"color":"Red","ccfLevel":7,"background":""},{"uid":30094,"name":"Ultraman_Z","slogan":"","badge":null,"isAdmin":false,"isBanned":false,"color":"Gray","ccfLevel":0,"background":""},{"uid":160113,"name":"Oliver_Heldens","slogan":"","badge":null,"isAdmin":false,"isBanned":false,"color":"Green","ccfLevel":4,"background":""},{"uid":157496,"name":"ksydom","slogan":"","badge":null,"isAdmin":false,"isBanned":false,"color":"Gray","ccfLevel":0,"background":""},{"uid":24081,"name":"Hydra_","slogan":"","badge":null,"isAdmin":false,"isBanned":false,"color":"Gray","ccfLevel":0,"background":""},{"uid":186489,"name":"EarthGiao","slogan":"acioi","badge":null,"isAdmin":false,"isBanned":false,"color":"Gray","ccfLevel":0,"background":"https://cdn.luogu.com.cn/upload/image_hosting/ih20iv2t.png"},{"uid":111528,"name":"hkr04","slogan":"睡觉中","badge":null,"isAdmin":false,"isBanned":false,"color":"Orange","ccfLevel":8,"background":""},{"uid":36788,"name":"4396瞎","slogan":"","badge":null,"isAdmin":false,"isBanned":false,"color":"Gray","ccfLevel":0,"background":""},{"uid":48611,"name":"_NoOne","slogan":"Valar morghulis Valar Dohaeris","badge":null,"isAdmin":false,"isBanned":false,"color":"Gray","ccfLevel":0,"background":"https://cdn.luogu.com.cn/upload/image_hosting/sledpmse.png"},{"uid":28939,"name":"Lyrics","slogan":"","badge":null,"isAdmin":false,"isBanned":false,"color":"Blue","ccfLevel":0,"background":""},{"uid":184681,"name":"cscy","slogan":"臭酸菜鱼","badge":null,"isAdmin":false,"isBanned":false,"color":"Gray","ccfLevel":4,"background":"https://cdn.luogu.com.cn/upload/image_hosting/oh8nwei9.png"},{"uid":122557,"name":"pyyyyyy","slogan":"都是鱼肉，只不过砧板不同罢了","badge":null,"isAdmin":false,"isBanned":false,"color":"Gray","ccfLevel":0,"background":"https://cdn.luogu.com.cn/upload/image_hosting/w79a16vj.png"},{"uid":60489,"name":"小菜鸟","slogan":"咕咕咕（","badge":null,"isAdmin":false,"isBanned":false,"color":"Orange","ccfLevel":7,"background":"https://cdn.luogu.com.cn/upload/image_hosting/om1iaovp.png"},{"uid":80679,"name":"Register","slogan":"","badge":null,"isAdmin":false,"isBanned":false,"color":"Red","ccfLevel":9,"background":"https://cdn.luogu.com.cn/upload/image_hosting/xmh9q0oz.png"},{"uid":28004,"name":"PBCWZCC","slogan":"做你自己","badge":null,"isAdmin":false,"isBanned":false,"color":"Gray","ccfLevel":0,"background":""},{"uid":78228,"name":"我没有小白","slogan":"","badge":null,"isAdmin":false,"isBanned":false,"color":"Green","ccfLevel":4,"background":""},{"uid":12472,"name":"Nekroz","slogan":"我是张旭腾，我牛的一批","badge":null,"isAdmin":false,"isBanned":false,"color":"Blue","ccfLevel":0,"background":""},{"uid":70545,"name":"Awar3ness","slogan":"","badge":null,"isAdmin":false,"isBanned":false,"color":"Blue","ccfLevel":0,"background":""},{"uid":54721,"name":"chengjintao","slogan":null,"badge":null,"isAdmin":false,"isBanned":false,"color":"Gray","ccfLevel":0,"background":""},{"uid":54636,"name":"Riven_Yasuo","slogan":null,"badge":null,"isAdmin":false,"isBanned":true,"color":"Gray","ccfLevel":0,"background":""},{"uid":39907,"name":"Rockdu","slogan":"","badge":null,"isAdmin":false,"isBanned":false,"color":"Gray","ccfLevel":7,"background":""},{"uid":38945,"name":"jimmylijiaji","slogan":null,"badge":null,"isAdmin":false,"isBanned":false,"color":"Gray","ccfLevel":0,"background":""},{"uid":17689,"name":"远航之曲","slogan":"","badge":null,"isAdmin":false,"isBanned":false,"color":"Gray","ccfLevel":7,"background":""},{"uid":14738,"name":"1124828077ccj","slogan":"","badge":null,"isAdmin":false,"isBanned":false,"color":"Green","ccfLevel":0,"background":""},{"uid":20604,"name":"litble","slogan":"苟……苟活者在淡红的血色中，会依稀看见微茫的希望（AFO)","badge":null,"isAdmin":false,"isBanned":false,"color":"Red","ccfLevel":10,"background":"https://cdn.luogu.com.cn/upload/image_hosting/v6zb1qvu.png"},{"uid":27138,"name":"mrkrnblsa","slogan":null,"badge":null,"isAdmin":false,"isBanned":true,"color":"Gray","ccfLevel":0,"background":""},{"uid":23388,"name":"kgrox","slogan":"","badge":null,"isAdmin":false,"isBanned":false,"color":"Gray","ccfLevel":0,"background":""},{"uid":8662,"name":"Mys_C_K","slogan":"","badge":null,"isAdmin":false,"isBanned":false,"color":"Gray","ccfLevel":0,"background":""},{"uid":13940,"name":"pupuvovovovovo","slogan":"这很个懒家伙，也留什有么下没","badge":null,"isAdmin":false,"isBanned":false,"color":"Gray","ccfLevel":0,"background":""},{"uid":22108,"name":"Leoo","slogan":"","badge":null,"isAdmin":false,"isBanned":false,"color":"Blue","ccfLevel":0,"background":""},{"uid":28023,"name":"McGrady","slogan":"","badge":null,"isAdmin":false,"isBanned":false,"color":"Gray","ccfLevel":0,"background":""},{"uid":41542,"name":"egret","slogan":"","badge":null,"isAdmin":false,"isBanned":false,"color":"Blue","ccfLevel":0,"background":""},{"uid":49776,"name":"chenxinyang2006","slogan":"macesuted","badge":null,"isAdmin":false,"isBanned":false,"color":"Red","ccfLevel":0,"background":""},{"uid":118869,"name":"dead_gun","slogan":"多情自古空余恨,好梦由来最易醒","badge":null,"isAdmin":false,"isBanned":false,"color":"Blue","ccfLevel":0,"background":"https://cdn.luogu.com.cn/upload/image_hosting/5cmnbsr3.png"},{"uid":116388,"name":"SFWR","slogan":"Everything you give will be rewarded.","badge":null,"isAdmin":false,"isBanned":false,"color":"Orange","ccfLevel":6,"background":""},{"uid":81690,"name":"EricWay1024","slogan":"code elegantly","badge":null,"isAdmin":false,"isBanned":false,"color":"Gray","ccfLevel":6,"background":""},{"uid":71463,"name":"Agumon_","slogan":"不想做一成不变的事","badge":null,"isAdmin":false,"isBanned":false,"color":"Gray","ccfLevel":0,"background":""},{"uid":56384,"name":"shadowice1984","slogan":"これが勘違いでも、これが勘違いでも","badge":null,"isAdmin":false,"isBanned":false,"color":"Red","ccfLevel":9,"background":"https://cdn.luogu.com.cn/upload/image_hosting/0rtqmqj7.png"},{"uid":17326,"name":"林志杰","slogan":null,"badge":null,"isAdmin":false,"isBanned":false,"color":"Gray","ccfLevel":0,"background":""},{"uid":20609,"name":"渡海","slogan":"","badge":null,"isAdmin":false,"isBanned":false,"color":"Gray","ccfLevel":0,"background":""},{"uid":27276,"name":"王将飞扬Cliffly","slogan":"","badge":null,"isAdmin":false,"isBanned":false,"color":"Gray","ccfLevel":0,"background":""}]}