{"count":24,"solutions":[{"uid":43486,"name":"hsfzLZH1","slogan":"我永远喜欢珂朵莉","badge":null,"isAdmin":false,"isBanned":false,"color":"Red","ccfLevel":7,"background":"https://cdn.luogu.com.cn/upload/image_hosting/6nwzxhli.png"},{"uid":28313,"name":"皎月半洒花","slogan":"在那之前，你要多想。","badge":"小花","isAdmin":false,"isBanned":false,"color":"Red","ccfLevel":7,"background":"https://cdn.luogu.com.cn/upload/image_hosting/9dk5cy40.png"},{"uid":60258,"name":"NCC79601","slogan":"To boldly go where no one has gone before.","badge":null,"isAdmin":false,"isBanned":false,"color":"Green","ccfLevel":7,"background":"https://cdn.luogu.com.cn/upload/image_hosting/bgoxbjnr.png"},{"uid":30066,"name":"Jianuo_Zhu","slogan":"这家伙很强，什么也不屑于留下","badge":null,"isAdmin":false,"isBanned":false,"color":"Gray","ccfLevel":6,"background":""},{"uid":21421,"name":"pantw","slogan":"","badge":null,"isAdmin":false,"isBanned":false,"color":"Orange","ccfLevel":7,"background":"https://cdn.luogu.com.cn/upload/image_hosting/g9lm4ooe.png"},{"uid":42156,"name":"feecle6418","slogan":"luogubot","badge":"机器人","isAdmin":true,"isBanned":false,"color":"Purple","ccfLevel":0,"background":"https://cdn.luogu.com.cn/upload/image_hosting/ch7k38hl.png"},{"uid":109401,"name":"宁_缺","slogan":"","badge":null,"isAdmin":false,"isBanned":false,"color":"Green","ccfLevel":6,"background":"https://cdn.luogu.com.cn/upload/image_hosting/vxryox09.png"},{"uid":53374,"name":"SuperJvRuo","slogan":"","badge":null,"isAdmin":false,"isBanned":false,"color":"Orange","ccfLevel":6,"background":""},{"uid":39863,"name":"引领天下","slogan":"用6年时间，讲好一个笑话。","badge":"魔酸","isAdmin":true,"isBanned":false,"color":"Purple","ccfLevel":5,"background":"https://cdn.luogu.com.cn/upload/image_hosting/swwvbxdm.png"},{"uid":9567,"name":"HOOCCOOH","slogan":"","badge":null,"isAdmin":false,"isBanned":false,"color":"Gray","ccfLevel":0,"background":""},{"uid":9431,"name":"cabasky","slogan":"","badge":null,"isAdmin":false,"isBanned":false,"color":"Gray","ccfLevel":0,"background":""},{"uid":23323,"name":"用户已注销","slogan":null,"badge":null,"isAdmin":false,"isBanned":false,"color":"Gray","ccfLevel":0,"background":""},{"uid":12159,"name":"Jobs","slogan":null,"badge":null,"isAdmin":false,"isBanned":false,"color":"Gray","ccfLevel":0,"background":""},{"uid":9168,"name":"kczno1","slogan":"","badge":null,"isAdmin":false,"isBanned":false,"color":"Gray","ccfLevel":0,"background":""},{"uid":8212,"name":"__stdcall","slogan":"","badge":null,"isAdmin":false,"isBanned":false,"color":"Red","ccfLevel":10,"background":""},{"uid":15702,"name":"rhdeng","slogan":"best is yet to come","badge":null,"isAdmin":false,"isBanned":false,"color":"Orange","ccfLevel":7,"background":"https://cdn.luogu.com.cn/upload/image_hosting/k58hymuj.png"},{"uid":36090,"name":"wenzhang","slogan":"","badge":null,"isAdmin":false,"isBanned":false,"color":"Gray","ccfLevel":0,"background":""},{"uid":73992,"name":"resftlmuttmotw","slogan":"来日方长，这个世界仍然很美丽。CSP加油","badge":null,"isAdmin":false,"isBanned":false,"color":"Gray","ccfLevel":0,"background":"https://cdn.luogu.com.cn/upload/image_hosting/hr0mide6.png"},{"uid":141791,"name":"Tony_Wong","slogan":"↑     这是个蒟蒻     ↑","badge":null,"isAdmin":false,"isBanned":false,"color":"Gray","ccfLevel":6,"background":"https://cdn.luogu.com.cn/upload/image_hosting/d75a5vm3.png"},{"uid":38859,"name":"Nero_Claudius","slogan":"唔姆唔姆","badge":null,"isAdmin":false,"isBanned":false,"color":"Gray","ccfLevel":0,"background":"https://cdn.luogu.com.cn/upload/image_hosting/46yc9s9q.png"},{"uid":43464,"name":"Creeper_LKF","slogan":"","badge":null,"isAdmin":false,"isBanned":false,"color":"Gray","ccfLevel":7,"background":""},{"uid":16975,"name":"tswdfop233","slogan":"","badge":null,"isAdmin":false,"isBanned":false,"color":"Gray","ccfLevel":0,"background":""},{"uid":24716,"name":"Beginner_df016","slogan":"","badge":null,"isAdmin":false,"isBanned":false,"color":"Gray","ccfLevel":0,"background":""},{"uid":33242,"name":"echo6342","slogan":"","badge":null,"isAdmin":false,"isBanned":false,"color":"Gray","ccfLevel":0,"background":"https://cdn.luogu.com.cn/upload/image_hosting/ml4hau7j.png"}]}