{"count":6,"solutions":[{"uid":108047,"name":"LlLlCc","slogan":"背井离乡，忍辱负重","badge":null,"isAdmin":false,"isBanned":false,"color":"Gray","ccfLevel":7,"background":""},{"uid":126484,"name":"first_fan","slogan":"Just Do It,But Not Just Do It.","badge":null,"isAdmin":false,"isBanned":false,"color":"Blue","ccfLevel":0,"background":"https://cdn.luogu.com.cn/upload/image_hosting/f61stx63.png"},{"uid":28810,"name":"King_of_gamers","slogan":"大圣此去欲何？踏南天碎凌霄！若一去不回？便一去不回！","badge":null,"isAdmin":false,"isBanned":false,"color":"Gray","ccfLevel":7,"background":""},{"uid":291706,"name":"GspTools","slogan":"或许早该说，AFO了","badge":null,"isAdmin":false,"isBanned":false,"color":"Blue","ccfLevel":0,"background":""},{"uid":13185,"name":"双管荧光灯","slogan":"楽園(はめつ)への花道をいざ照らせ","badge":null,"isAdmin":false,"isBanned":false,"color":"Gray","ccfLevel":10,"background":""},{"uid":16817,"name":"winmt","slogan":"","badge":null,"isAdmin":false,"isBanned":false,"color":"Gray","ccfLevel":0,"background":""}]}