{"count":3,"solutions":[{"uid":846190,"name":"xyx0817","slogan":"这个菜鸟很懒啥都没留下","badge":null,"isAdmin":false,"isBanned":false,"color":"Green","ccfLevel":0,"background":""},{"uid":846379,"name":"fangyicheng1216","slogan":"蒟蒻一只","badge":null,"isAdmin":false,"isBanned":false,"color":"Red","ccfLevel":0,"background":""},{"uid":846287,"name":"Code_Fish_Hp","slogan":"江湖一笑，浪滔滔，红尘尽忘掉","badge":"","isAdmin":false,"isBanned":false,"color":"Orange","ccfLevel":0,"background":"https://cdn.luogu.com.cn/upload/image_hosting/iwrfdfh3.png"}]}