{"count":35,"solutions":[{"uid":325319,"name":"ohnmachesya","slogan":"日子长新，未来不远。","badge":null,"isAdmin":false,"isBanned":false,"color":"Gray","ccfLevel":0,"background":"https://cdn.luogu.com.cn/upload/image_hosting/ss9n6jxv.png"},{"uid":559919,"name":"FQR_","slogan":"　","badge":null,"isAdmin":false,"isBanned":false,"color":"Red","ccfLevel":5,"background":"https://cdn.luogu.com.cn/upload/image_hosting/ee7uh8xx.png"},{"uid":250983,"name":"wzmzmhk","slogan":"AFO","badge":null,"isAdmin":false,"isBanned":false,"color":"Blue","ccfLevel":0,"background":""},{"uid":724052,"name":"Only_Remember_Z","slogan":"要来一颗 APTX4869 吗？","badge":null,"isAdmin":false,"isBanned":false,"color":"Red","ccfLevel":5,"background":"https://cdn.luogu.com.cn/upload/image_hosting/8jd839b2.png"},{"uid":478585,"name":"Dregen_Yor","slogan":"那时，我开始使用名叫数学的武器。但是，那种武器往往过于巨大，很多时候不能灵活操控。这种感觉正如我很难操控自己年轻时的青涩，很难控制对他们的思念一样。","badge":null,"isAdmin":false,"isBanned":false,"color":"Orange","ccfLevel":4,"background":"https://cdn.luogu.com.cn/upload/image_hosting/lgnu3xax.png"},{"uid":505578,"name":"Chronomaly_Atlandis","slogan":"月球的同胞们呀。欢迎来到余的黄金剧场！唔姆、唔姆！","badge":null,"isAdmin":false,"isBanned":false,"color":"Gray","ccfLevel":0,"background":""},{"uid":525374,"name":"sgl654321","slogan":"风过雨停，天又放晴","badge":"追梦 Oier","isAdmin":false,"isBanned":false,"color":"Red","ccfLevel":0,"background":""},{"uid":661044,"name":"_saltFish_","slogan":"嗯？","badge":null,"isAdmin":false,"isBanned":false,"color":"Orange","ccfLevel":0,"background":"https://cdn.luogu.com.cn/upload/image_hosting/gzec5gaf.png"},{"uid":324350,"name":"xiaomuyun","slogan":"精神极度波动，抽象起来了 | I + WE = Full I | 互关，忘关私","badge":null,"isAdmin":false,"isBanned":false,"color":"Orange","ccfLevel":5,"background":"https://cdn.luogu.com.cn/upload/image_hosting/yiox1jsq.png"},{"uid":743048,"name":"Lovely_Ran","slogan":"qwq | 私信互关","badge":null,"isAdmin":false,"isBanned":false,"color":"Cheater","ccfLevel":6,"background":""},{"uid":542282,"name":"lrqlrq250","slogan":"Why does this chicken play basketball ???","badge":null,"isAdmin":false,"isBanned":false,"color":"Red","ccfLevel":0,"background":""},{"uid":384000,"name":"DANIEL_x_","slogan":"","badge":null,"isAdmin":false,"isBanned":false,"color":"Orange","ccfLevel":0,"background":""},{"uid":322620,"name":"_SHM_","slogan":"不拿蓝勾不改个性签名","badge":null,"isAdmin":false,"isBanned":false,"color":"Red","ccfLevel":3,"background":"https://cdn.luogu.com.cn/upload/image_hosting/u1irbyvf.png"},{"uid":381189,"name":"xiezihanAKIOI","slogan":"IOI不AK我不改个性签名","badge":null,"isAdmin":false,"isBanned":false,"color":"Green","ccfLevel":3,"background":""},{"uid":180406,"name":"lilong","slogan":"不拿蓝√不改个性签名 || 互关qwq","badge":null,"isAdmin":false,"isBanned":false,"color":"Red","ccfLevel":5,"background":"https://cdn.luogu.com.cn/upload/image_hosting/6jjadway.png"},{"uid":142969,"name":"GI录像机","slogan":"星辰遥不可及，于是我握紧长枪，瞄准天际","badge":null,"isAdmin":false,"isBanned":false,"color":"Red","ccfLevel":5,"background":"https://cdn.luogu.com.cn/upload/image_hosting/7vh15t1b.png"},{"uid":545924,"name":"chwu","slogan":"Destiny never leave!","badge":"Destiny","isAdmin":false,"isBanned":false,"color":"Orange","ccfLevel":0,"background":""},{"uid":673601,"name":"FWT__FFT","slogan":null,"badge":null,"isAdmin":false,"isBanned":true,"color":"Gray","ccfLevel":0,"background":""},{"uid":307987,"name":"ztytql","slogan":"？6","badge":null,"isAdmin":false,"isBanned":false,"color":"Orange","ccfLevel":4,"background":"https://cdn.luogu.com.cn/upload/image_hosting/twivoxvv.png"},{"uid":658291,"name":"chengning0909","slogan":"Haibara 超级可爱的好吧","badge":null,"isAdmin":false,"isBanned":false,"color":"Red","ccfLevel":4,"background":"https://cdn.luogu.com.cn/upload/image_hosting/0fbr12fc.png"},{"uid":251870,"name":"LazYQwQ","slogan":"义已失 吾亦死   逸一时 误一世","badge":null,"isAdmin":false,"isBanned":false,"color":"Gray","ccfLevel":4,"background":"https://cdn.luogu.com.cn/upload/image_hosting/fitjkpbc.png"},{"uid":663517,"name":"Jeremiahy","slogan":"Good moring!","badge":null,"isAdmin":false,"isBanned":false,"color":"Orange","ccfLevel":0,"background":""},{"uid":102849,"name":"Deft_t","slogan":"","badge":null,"isAdmin":false,"isBanned":false,"color":"Orange","ccfLevel":0,"background":""},{"uid":374769,"name":"Faith_toChange","slogan":"","badge":null,"isAdmin":false,"isBanned":false,"color":"Green","ccfLevel":0,"background":"https://cdn.luogu.com.cn/upload/image_hosting/mnx73nu4.png"},{"uid":448593,"name":"ldh081122","slogan":"OI 菜||数学菜||whk菜||啥用没有的一个废人","badge":null,"isAdmin":false,"isBanned":false,"color":"Orange","ccfLevel":4,"background":"https://cdn.luogu.com.cn/upload/image_hosting/nz6i7bln.png"},{"uid":668002,"name":"sw2022","slogan":"​","badge":null,"isAdmin":false,"isBanned":false,"color":"Red","ccfLevel":4,"background":""},{"uid":119707,"name":"cachejtt","slogan":"破碎了的梦想，依旧是前行的力量。","badge":null,"isAdmin":false,"isBanned":false,"color":"Green","ccfLevel":5,"background":""},{"uid":387840,"name":"happy_dengziyue","slogan":"GD OIer|路漫漫其修远兮，吾将上下而求索","badge":null,"isAdmin":false,"isBanned":false,"color":"Red","ccfLevel":6,"background":"https://cdn.luogu.com.cn/upload/image_hosting/091bqm3j.png"},{"uid":393934,"name":"zhicheng","slogan":"","badge":null,"isAdmin":false,"isBanned":false,"color":"Red","ccfLevel":5,"background":""},{"uid":203453,"name":"Foofish","slogan":"夕阳中那几欲落泪般的赤红","badge":null,"isAdmin":false,"isBanned":false,"color":"Green","ccfLevel":5,"background":"https://cdn.luogu.com.cn/upload/image_hosting/obk9x8mu.png"},{"uid":221987,"name":"arkerny","slogan":"伦家明明就似珂爱的女孩纸呀……","badge":null,"isAdmin":false,"isBanned":false,"color":"Orange","ccfLevel":4,"background":"https://cdn.luogu.com.cn/upload/image_hosting/jpftobng.png"},{"uid":339299,"name":"osfly","slogan":"ㅤ","badge":null,"isAdmin":false,"isBanned":false,"color":"Orange","ccfLevel":5,"background":"https://cdn.luogu.com.cn/upload/image_hosting/k2mzjvde.png"},{"uid":298208,"name":"BorisDimitri","slogan":"AFOed","badge":null,"isAdmin":false,"isBanned":false,"color":"Green","ccfLevel":5,"background":"https://cdn.luogu.com.cn/upload/image_hosting/s74cvkuc.png"},{"uid":555301,"name":"zfx1569_HCl_2023","slogan":"FQYZ8.5 05 | EXL | 有事私信小号599718 | 请取关我","badge":null,"isAdmin":false,"isBanned":false,"color":"Red","ccfLevel":0,"background":"https://cdn.luogu.com.cn/upload/image_hosting/fi31sg25.png"},{"uid":492010,"name":"Algae_qwq","slogan":"有事联系Algae","badge":null,"isAdmin":false,"isBanned":false,"color":"Green","ccfLevel":0,"background":"https://cdn.luogu.com.cn/upload/image_hosting/e05kk1d1.png"}]}