{"count":6,"solutions":[{"uid":55078,"name":"YLWang","slogan":"别等到一千年以后 所有人都遗忘了我","badge":null,"isAdmin":false,"isBanned":false,"color":"Red","ccfLevel":9,"background":"https://cdn.luogu.com.cn/upload/image_hosting/zozg6h7w.png"},{"uid":151935,"name":"Rainbow_qwq","slogan":"皇帝不急太监急","badge":null,"isAdmin":false,"isBanned":false,"color":"Red","ccfLevel":0,"background":"https://cdn.luogu.com.cn/upload/image_hosting/1d3pwj3u.png"},{"uid":184084,"name":"_Freedom_","slogan":"摸鱼的时间想想 zh_x 甩你几条街","badge":null,"isAdmin":false,"isBanned":false,"color":"Orange","ccfLevel":7,"background":"https://cdn.luogu.com.cn/upload/image_hosting/b2kapq47.png"},{"uid":340632,"name":"Cry_For_theMoon","slogan":"无趣","badge":null,"isAdmin":false,"isBanned":false,"color":"Red","ccfLevel":8,"background":"https://cdn.luogu.com.cn/upload/image_hosting/li65p6b0.png"},{"uid":117771,"name":"intel_core","slogan":"To be or not to be.","badge":null,"isAdmin":false,"isBanned":false,"color":"Red","ccfLevel":7,"background":"https://cdn.luogu.com.cn/upload/image_hosting/qfpvlqta.png"},{"uid":88735,"name":"寒鸽儿","slogan":"寒鸽儿gugugu~","badge":null,"isAdmin":false,"isBanned":false,"color":"Green","ccfLevel":0,"background":"https://cdn.luogu.com.cn/upload/image_hosting/j173ms24.png"}]}