{"count":7,"solutions":[{"uid":99640,"name":"smallfang","slogan":"可爱。","badge":null,"isAdmin":false,"isBanned":false,"color":"Orange","ccfLevel":0,"background":"https://cdn.luogu.com.cn/upload/image_hosting/kxu5852t.png"},{"uid":387836,"name":"dengzijun","slogan":"以代码为笔，绘美好画卷。","badge":null,"isAdmin":false,"isBanned":false,"color":"Red","ccfLevel":5,"background":"https://cdn.luogu.com.cn/upload/image_hosting/4z0j3z9a.png"},{"uid":349333,"name":"zhenliu","slogan":"我最喜欢叶瑄！！","badge":null,"isAdmin":false,"isBanned":false,"color":"Gray","ccfLevel":0,"background":"https://cdn.luogu.com.cn/upload/image_hosting/qdsz1520.png"},{"uid":142548,"name":"int32","slogan":"战战兢兢，如临深渊，如履薄冰。","badge":null,"isAdmin":false,"isBanned":false,"color":"Green","ccfLevel":0,"background":"https://cdn.luogu.com.cn/upload/image_hosting/v3ovuo8p.png"},{"uid":424052,"name":"reailikezhu","slogan":"这个家伙很喜欢睡觉，什么都没有留下","badge":null,"isAdmin":false,"isBanned":false,"color":"Gray","ccfLevel":4,"background":""},{"uid":247202,"name":"OnlyExtreme","slogan":"我绝对应该也只能应该学文化课","badge":null,"isAdmin":false,"isBanned":false,"color":"Green","ccfLevel":5,"background":"https://cdn.luogu.com.cn/upload/image_hosting/4a0mrfdb.png"},{"uid":439136,"name":"jinxdtaiy","slogan":"来不及讲，故事多跌宕。","badge":null,"isAdmin":false,"isBanned":false,"color":"Green","ccfLevel":4,"background":""}]}