{"count":16,"solutions":[{"uid":82213,"name":"defense","slogan":"这个家伙很菜，什么也没有留下","badge":null,"isAdmin":false,"isBanned":false,"color":"Gray","ccfLevel":0,"background":""},{"uid":186034,"name":"Callous_Murder","slogan":null,"badge":null,"isAdmin":false,"isBanned":true,"color":"Blue","ccfLevel":0,"background":""},{"uid":305891,"name":"Warp","slogan":"","badge":null,"isAdmin":false,"isBanned":false,"color":"Red","ccfLevel":5,"background":"https://cdn.luogu.com.cn/upload/image_hosting/auym5w3i.png"},{"uid":192818,"name":"Sea_Level","slogan":"繁花似锦觅安宁，淡云流水度此生。","badge":null,"isAdmin":false,"isBanned":false,"color":"Blue","ccfLevel":0,"background":"https://cdn.luogu.com.cn/upload/image_hosting/weg3n3iu.png"},{"uid":231169,"name":"Laser_Crystal","slogan":"","badge":null,"isAdmin":false,"isBanned":false,"color":"Orange","ccfLevel":6,"background":""},{"uid":167010,"name":"Juvenile","slogan":"AFO","badge":null,"isAdmin":false,"isBanned":false,"color":"Blue","ccfLevel":0,"background":"https://cdn.luogu.com.cn/upload/image_hosting/k18h8j2r.png"},{"uid":240191,"name":"MY（一名蒟蒻）","slogan":"你数据结构都用错了，怎么改都是没用的。","badge":null,"isAdmin":false,"isBanned":false,"color":"Gray","ccfLevel":6,"background":"https://cdn.luogu.com.cn/upload/image_hosting/p9pety6h.png"},{"uid":191666,"name":"Cult_style","slogan":"","badge":null,"isAdmin":false,"isBanned":false,"color":"Gray","ccfLevel":0,"background":""},{"uid":360511,"name":"UperFicial","slogan":"尾声","badge":null,"isAdmin":false,"isBanned":false,"color":"Red","ccfLevel":0,"background":"https://cdn.luogu.com.cn/upload/image_hosting/idevgvvu.png"},{"uid":180790,"name":"zhzzhzzzz","slogan":"别说我自闭了，我从来没有自开过","badge":null,"isAdmin":false,"isBanned":false,"color":"Green","ccfLevel":3,"background":"https://cdn.luogu.com.cn/upload/image_hosting/2y54xzy2.png"},{"uid":56916,"name":"违规用户名U56916","slogan":"故地重游，还是怀念","badge":null,"isAdmin":false,"isBanned":false,"color":"Gray","ccfLevel":0,"background":""},{"uid":32894,"name":"SKTT1Faker","slogan":"","badge":null,"isAdmin":false,"isBanned":false,"color":"Gray","ccfLevel":0,"background":""},{"uid":365028,"name":"DreamerP","slogan":"人不行不怪路不平 大不了凹他个几千遍 总会收","badge":null,"isAdmin":false,"isBanned":false,"color":"Green","ccfLevel":4,"background":"https://cdn.luogu.com.cn/upload/image_hosting/x4uclr8u.png"},{"uid":229636,"name":"百里狂生","slogan":"code is not easy but not difficult","badge":null,"isAdmin":false,"isBanned":false,"color":"Blue","ccfLevel":0,"background":"https://cdn.luogu.com.cn/upload/image_hosting/vywgxxex.png"},{"uid":94973,"name":"冰桨","slogan":"","badge":null,"isAdmin":false,"isBanned":false,"color":"Blue","ccfLevel":0,"background":""},{"uid":32842,"name":"Mychael","slogan":"AFO","badge":null,"isAdmin":false,"isBanned":false,"color":"Gray","ccfLevel":8,"background":""}]}