{"count":4,"solutions":[{"uid":95624,"name":"HPXXZYY","slogan":"笑看世事似水变迁","badge":null,"isAdmin":false,"isBanned":false,"color":"Orange","ccfLevel":7,"background":"https://cdn.luogu.com.cn/upload/image_hosting/2l40ew50.png"},{"uid":213841,"name":"Steadywelkin","slogan":"The darkest time is that before the dawn.","badge":null,"isAdmin":false,"isBanned":false,"color":"Green","ccfLevel":7,"background":"https://cdn.luogu.com.cn/upload/image_hosting/f26u44w7.png"},{"uid":77211,"name":"i9_7980XE","slogan":null,"badge":null,"isAdmin":false,"isBanned":true,"color":"Gray","ccfLevel":0,"background":""},{"uid":707914,"name":"Siteyava_145","slogan":"","badge":null,"isAdmin":false,"isBanned":false,"color":"Orange","ccfLevel":0,"background":"https://cdn.luogu.com.cn/upload/image_hosting/wf2ev18r.png"}]}