{"count":4,"solutions":[{"uid":551108,"name":"Zhang_bingjia","slogan":"旁观拍手笑疏狂，疏又何妨，狂又何妨？","badge":null,"isAdmin":false,"isBanned":false,"color":"Red","ccfLevel":3,"background":"https://cdn.luogu.com.cn/upload/image_hosting/zunfdl1q.png"},{"uid":363353,"name":"pearchen","slogan":"狼よ目を覚ませ","badge":null,"isAdmin":false,"isBanned":false,"color":"Red","ccfLevel":4,"background":"https://cdn.luogu.com.cn/upload/image_hosting/jkjat2e3.png"},{"uid":478861,"name":"Gumbo","slogan":"不务正业&大模拟神教&SMOI出题团 团主","badge":null,"isAdmin":false,"isBanned":false,"color":"Red","ccfLevel":6,"background":""},{"uid":726395,"name":"ztntonny","slogan":"这个人很勤奋………ด้้้้้็้้้็็็็็้้้้้็็็็็้้้้้้็็็็็้้้้้็็็็็้้้้้้็็็็็้้้้้็็็็็้้้้้้็็็็็้้้้้็็็็็้้้้้้็","badge":null,"isAdmin":false,"isBanned":false,"color":"Red","ccfLevel":4,"background":"https://cdn.luogu.com.cn/upload/image_hosting/y6e6sxbi.png"}]}