{"count":45,"solutions":[{"uid":19722,"name":"fy0123","slogan":"","badge":null,"isAdmin":false,"isBanned":false,"color":"Orange","ccfLevel":7,"background":""},{"uid":32121,"name":"Lpy_Now","slogan":"","badge":null,"isAdmin":false,"isBanned":false,"color":"Green","ccfLevel":4,"background":""},{"uid":50871,"name":"Euler_Pursuer","slogan":"如果命运是块顽石，我就化为大锤，将它砸得粉碎！","badge":null,"isAdmin":false,"isBanned":false,"color":"Orange","ccfLevel":6,"background":"https://cdn.luogu.com.cn/upload/image_hosting/8uegg9iq.png"},{"uid":64288,"name":"旋转卡壳","slogan":"","badge":null,"isAdmin":false,"isBanned":false,"color":"Gray","ccfLevel":0,"background":""},{"uid":65363,"name":"一扶苏一","slogan":"执念","badge":"扶咕咕","isAdmin":true,"isBanned":false,"color":"Purple","ccfLevel":7,"background":""},{"uid":63019,"name":"星星之火","slogan":"","badge":null,"isAdmin":false,"isBanned":false,"color":"Gray","ccfLevel":0,"background":""},{"uid":115864,"name":"NaCly_Fish","slogan":"北海虽赊，扶摇可接。","badge":"绒布球","isAdmin":false,"isBanned":false,"color":"Red","ccfLevel":6,"background":"https://cdn.luogu.com.cn/upload/image_hosting/gc0n2r47.png"},{"uid":126376,"name":"Ireliaღ","slogan":"逝去的是刀锋，不变的是意志","badge":null,"isAdmin":false,"isBanned":false,"color":"Orange","ccfLevel":7,"background":"https://cdn.luogu.com.cn/upload/image_hosting/t8jiqhn2.png"},{"uid":61325,"name":"FlashHu","slogan":"","badge":null,"isAdmin":false,"isBanned":false,"color":"Gray","ccfLevel":8,"background":""},{"uid":57014,"name":"Nemlit","slogan":"自能生羽翼，何必仰云梯。","badge":null,"isAdmin":false,"isBanned":false,"color":"Red","ccfLevel":9,"background":"https://cdn.luogu.com.cn/upload/image_hosting/6gmbv02h.png"},{"uid":218449,"name":"Xx_queue","slogan":"这个家伙很懒，但他还是留下了这句话","badge":null,"isAdmin":false,"isBanned":false,"color":"Green","ccfLevel":4,"background":"https://cdn.luogu.com.cn/upload/image_hosting/a50pmu27.png"},{"uid":58363,"name":"Bronya19C","slogan":"It was the best of times, it was the worst of times","badge":null,"isAdmin":false,"isBanned":false,"color":"Red","ccfLevel":7,"background":"https://cdn.luogu.com.cn/upload/image_hosting/oahfm5eb.png"},{"uid":67718,"name":"G我就是菜G","slogan":"这个家伙不懒，但是还是什么都没留下","badge":null,"isAdmin":false,"isBanned":false,"color":"Green","ccfLevel":6,"background":""},{"uid":97385,"name":"向noip冲刺","slogan":"","badge":null,"isAdmin":false,"isBanned":false,"color":"Gray","ccfLevel":0,"background":""},{"uid":63539,"name":"wjyyy","slogan":"不能因为太阳光芒万丈而不敢仰望。","badge":null,"isAdmin":false,"isBanned":false,"color":"Red","ccfLevel":9,"background":""},{"uid":30036,"name":"Soulist","slogan":"再见了","badge":null,"isAdmin":false,"isBanned":false,"color":"Red","ccfLevel":9,"background":"https://cdn.luogu.com.cn/upload/image_hosting/cexl6cpz.png"},{"uid":29470,"name":"qzp666","slogan":"","badge":null,"isAdmin":false,"isBanned":false,"color":"Gray","ccfLevel":0,"background":""},{"uid":66965,"name":"Juan_feng","slogan":"qwqwq","badge":null,"isAdmin":false,"isBanned":false,"color":"Gray","ccfLevel":0,"background":""},{"uid":50047,"name":"Bartholomew","slogan":"","badge":null,"isAdmin":false,"isBanned":false,"color":"Gray","ccfLevel":0,"background":""},{"uid":114320,"name":"落汐","slogan":"再见","badge":null,"isAdmin":false,"isBanned":false,"color":"Green","ccfLevel":0,"background":"https://cdn.luogu.com.cn/upload/image_hosting/8elmmjno.png"},{"uid":49458,"name":"木木！","slogan":"那不该在时间中存在的，便经不住时间的洗礼","badge":null,"isAdmin":false,"isBanned":false,"color":"Gray","ccfLevel":0,"background":"https://cdn.luogu.com.cn/upload/image_hosting/u524lm65.png"},{"uid":159730,"name":"Sophon","slogan":"独身の王です。独身万歳。","badge":null,"isAdmin":false,"isBanned":false,"color":"Blue","ccfLevel":0,"background":"https://cdn.luogu.com.cn/upload/image_hosting/s04cel7a.png"},{"uid":54916,"name":"I_AM_HelloWord","slogan":"","badge":null,"isAdmin":false,"isBanned":false,"color":"Gray","ccfLevel":0,"background":""},{"uid":77131,"name":"nth_element","slogan":"AFO","badge":null,"isAdmin":false,"isBanned":false,"color":"Gray","ccfLevel":5,"background":"https://cdn.luogu.com.cn/upload/image_hosting/v6hdv9o9.png"},{"uid":36933,"name":"zhy12138","slogan":"AFOed","badge":null,"isAdmin":false,"isBanned":false,"color":"Red","ccfLevel":9,"background":"https://cdn.luogu.com.cn/upload/image_hosting/jd9om74m.png"},{"uid":66915,"name":"Tyher","slogan":"SJTU在读","badge":null,"isAdmin":false,"isBanned":false,"color":"Gray","ccfLevel":7,"background":""},{"uid":29502,"name":"YangHao","slogan":"","badge":null,"isAdmin":false,"isBanned":false,"color":"Blue","ccfLevel":0,"background":""},{"uid":73992,"name":"resftlmuttmotw","slogan":"来日方长，这个世界仍然很美丽。CSP加油","badge":null,"isAdmin":false,"isBanned":false,"color":"Gray","ccfLevel":0,"background":"https://cdn.luogu.com.cn/upload/image_hosting/hr0mide6.png"},{"uid":49776,"name":"chenxinyang2006","slogan":"macesuted","badge":null,"isAdmin":false,"isBanned":false,"color":"Red","ccfLevel":0,"background":""},{"uid":27924,"name":"xukuan","slogan":"每日一膜hehezhou","badge":null,"isAdmin":false,"isBanned":false,"color":"Blue","ccfLevel":0,"background":""},{"uid":50215,"name":"maomao","slogan":"大学生","badge":null,"isAdmin":false,"isBanned":false,"color":"Green","ccfLevel":6,"background":""},{"uid":38055,"name":"Npse_D","slogan":"","badge":null,"isAdmin":false,"isBanned":false,"color":"Gray","ccfLevel":0,"background":""},{"uid":38859,"name":"Nero_Claudius","slogan":"唔姆唔姆","badge":null,"isAdmin":false,"isBanned":false,"color":"Gray","ccfLevel":0,"background":"https://cdn.luogu.com.cn/upload/image_hosting/46yc9s9q.png"},{"uid":56672,"name":"枫林晚","slogan":"","badge":null,"isAdmin":false,"isBanned":false,"color":"Orange","ccfLevel":9,"background":"https://cdn.luogu.com.cn/upload/image_hosting/9pojt44m.png"},{"uid":27986,"name":"jxcakak","slogan":"","badge":null,"isAdmin":false,"isBanned":false,"color":"Blue","ccfLevel":0,"background":""},{"uid":84788,"name":"Jeblqr","slogan":"","badge":null,"isAdmin":false,"isBanned":false,"color":"Gray","ccfLevel":5,"background":""},{"uid":130842,"name":"Grind_1","slogan":"Calm","badge":null,"isAdmin":false,"isBanned":false,"color":"Blue","ccfLevel":0,"background":""},{"uid":153898,"name":"Treaker","slogan":"后会无期","badge":null,"isAdmin":false,"isBanned":false,"color":"Gray","ccfLevel":0,"background":"https://cdn.luogu.com.cn/upload/image_hosting/avrdskps.png"},{"uid":33543,"name":"ynyuje","slogan":"","badge":null,"isAdmin":false,"isBanned":false,"color":"Gray","ccfLevel":6,"background":""},{"uid":59032,"name":"轻尘","slogan":"","badge":null,"isAdmin":false,"isBanned":false,"color":"Gray","ccfLevel":0,"background":""},{"uid":41781,"name":"bztMinamoto","slogan":"","badge":null,"isAdmin":false,"isBanned":false,"color":"Green","ccfLevel":0,"background":""},{"uid":46982,"name":"Angora","slogan":"","badge":null,"isAdmin":false,"isBanned":false,"color":"Gray","ccfLevel":0,"background":""},{"uid":60867,"name":"heyongxin","slogan":"","badge":null,"isAdmin":false,"isBanned":false,"color":"Green","ccfLevel":6,"background":""},{"uid":25815,"name":"封癫","slogan":"","badge":null,"isAdmin":false,"isBanned":false,"color":"Gray","ccfLevel":7,"background":""},{"uid":52576,"name":"moye到碗里来","slogan":"","badge":null,"isAdmin":false,"isBanned":false,"color":"Gray","ccfLevel":0,"background":""}]}