{"count":42,"solutions":[{"uid":50871,"name":"Euler_Pursuer","slogan":"如果命运是块顽石，我就化为大锤，将它砸得粉碎！","badge":null,"isAdmin":false,"isBanned":false,"color":"Orange","ccfLevel":6,"background":"https://cdn.luogu.com.cn/upload/image_hosting/8uegg9iq.png"},{"uid":51621,"name":"Altria_Pendragon_","slogan":"1296","badge":null,"isAdmin":false,"isBanned":false,"color":"Gray","ccfLevel":0,"background":""},{"uid":44424,"name":"zhutier","slogan":"窝窝头，一块钱四个，嘿嘿","badge":null,"isAdmin":false,"isBanned":false,"color":"Blue","ccfLevel":0,"background":""},{"uid":38235,"name":"yyy14159","slogan":"","badge":null,"isAdmin":false,"isBanned":false,"color":"Blue","ccfLevel":0,"background":""},{"uid":30889,"name":"DavidW","slogan":"","badge":null,"isAdmin":false,"isBanned":false,"color":"Gray","ccfLevel":7,"background":""},{"uid":20578,"name":"ningyuheng","slogan":"从来如此，便对么？","badge":null,"isAdmin":false,"isBanned":false,"color":"Gray","ccfLevel":9,"background":""},{"uid":130745,"name":"HXH2148","slogan":"一个瑟瑟发抖的OIer","badge":null,"isAdmin":false,"isBanned":false,"color":"Blue","ccfLevel":0,"background":""},{"uid":47863,"name":"Imakf","slogan":"","badge":null,"isAdmin":false,"isBanned":false,"color":"Orange","ccfLevel":0,"background":"https://cdn.luogu.com.cn/upload/image_hosting/3vs5xj8v.png"},{"uid":129782,"name":"Lee02","slogan":"","badge":null,"isAdmin":false,"isBanned":false,"color":"Gray","ccfLevel":0,"background":""},{"uid":21283,"name":"yybyyb","slogan":"","badge":null,"isAdmin":false,"isBanned":false,"color":"Gray","ccfLevel":10,"background":""},{"uid":122927,"name":"Jelly_Goat","slogan":"小金羊！","badge":null,"isAdmin":false,"isBanned":false,"color":"Gray","ccfLevel":3,"background":""},{"uid":86409,"name":"Night_star","slogan":"Ad astra per aspera","badge":null,"isAdmin":false,"isBanned":false,"color":"Green","ccfLevel":5,"background":"https://cdn.luogu.com.cn/upload/image_hosting/7pre8bi9.png"},{"uid":126929,"name":"nenugdi","slogan":"","badge":null,"isAdmin":false,"isBanned":false,"color":"Blue","ccfLevel":0,"background":""},{"uid":33376,"name":"旋风猪皮","slogan":"读书不作儒生酸，跃马西入金城关","badge":null,"isAdmin":false,"isBanned":false,"color":"Green","ccfLevel":0,"background":""},{"uid":32842,"name":"Mychael","slogan":"AFO","badge":null,"isAdmin":false,"isBanned":false,"color":"Gray","ccfLevel":8,"background":""},{"uid":20116,"name":"never_see","slogan":"","badge":null,"isAdmin":false,"isBanned":false,"color":"Gray","ccfLevel":0,"background":""},{"uid":13180,"name":"amazingOZR","slogan":"","badge":null,"isAdmin":false,"isBanned":false,"color":"Gray","ccfLevel":0,"background":""},{"uid":165949,"name":"jinyijiang","slogan":"在→边点个关注吧QwQ","badge":null,"isAdmin":false,"isBanned":false,"color":"Gray","ccfLevel":5,"background":""},{"uid":121618,"name":"Accoty_AM","slogan":"这个家伙真菜， 大家快嘲笑它","badge":null,"isAdmin":false,"isBanned":false,"color":"Orange","ccfLevel":6,"background":"https://cdn.luogu.com.cn/upload/image_hosting/onlxgcvr.png"},{"uid":131851,"name":"上杉","slogan":"","badge":null,"isAdmin":false,"isBanned":false,"color":"Gray","ccfLevel":4,"background":""},{"uid":66181,"name":"Celebrate","slogan":"","badge":null,"isAdmin":false,"isBanned":false,"color":"Blue","ccfLevel":0,"background":""},{"uid":43848,"name":"Believe_Horizon","slogan":"","badge":null,"isAdmin":false,"isBanned":false,"color":"Gray","ccfLevel":0,"background":""},{"uid":11757,"name":"手链剖分","slogan":"","badge":null,"isAdmin":false,"isBanned":false,"color":"Blue","ccfLevel":0,"background":""},{"uid":43355,"name":"zschhh","slogan":"","badge":null,"isAdmin":false,"isBanned":false,"color":"Blue","ccfLevel":0,"background":""},{"uid":19778,"name":"water_mi","slogan":"","badge":null,"isAdmin":false,"isBanned":false,"color":"Blue","ccfLevel":0,"background":""},{"uid":19551,"name":"NishikinoMaki","slogan":"","badge":null,"isAdmin":false,"isBanned":false,"color":"Gray","ccfLevel":0,"background":""},{"uid":4865,"name":"Mr_Li","slogan":"","badge":null,"isAdmin":false,"isBanned":false,"color":"Gray","ccfLevel":8,"background":""},{"uid":7608,"name":"htt_wbsxg2","slogan":"","badge":null,"isAdmin":false,"isBanned":false,"color":"Gray","ccfLevel":0,"background":""},{"uid":68987,"name":"kion","slogan":"https://www.cnblogs.com/kion/","badge":null,"isAdmin":false,"isBanned":false,"color":"Blue","ccfLevel":0,"background":""},{"uid":37009,"name":"xdc呀","slogan":"","badge":null,"isAdmin":false,"isBanned":false,"color":"Green","ccfLevel":4,"background":""},{"uid":144523,"name":"JohnJoeZhu","slogan":"我要认真学习whk！！！","badge":null,"isAdmin":false,"isBanned":false,"color":"Orange","ccfLevel":7,"background":"https://cdn.luogu.com.cn/upload/image_hosting/lfiwonj2.png"},{"uid":65971,"name":"mrgogoup","slogan":"","badge":null,"isAdmin":false,"isBanned":false,"color":"Blue","ccfLevel":0,"background":""},{"uid":38313,"name":"chenkaixing","slogan":null,"badge":null,"isAdmin":false,"isBanned":false,"color":"Gray","ccfLevel":0,"background":""},{"uid":19015,"name":"bobble","slogan":"","badge":null,"isAdmin":false,"isBanned":false,"color":"Blue","ccfLevel":0,"background":""},{"uid":23087,"name":"Tgotp","slogan":"","badge":null,"isAdmin":false,"isBanned":false,"color":"Orange","ccfLevel":9,"background":""},{"uid":790,"name":"约修亚_RK","slogan":"","badge":null,"isAdmin":false,"isBanned":false,"color":"Gray","ccfLevel":6,"background":""},{"uid":10025,"name":"神一般的世界","slogan":"","badge":null,"isAdmin":false,"isBanned":false,"color":"Gray","ccfLevel":0,"background":""},{"uid":14129,"name":"Ste_","slogan":"","badge":null,"isAdmin":false,"isBanned":false,"color":"Gray","ccfLevel":0,"background":""},{"uid":8874,"name":"Kwork","slogan":null,"badge":null,"isAdmin":false,"isBanned":false,"color":"Gray","ccfLevel":0,"background":""},{"uid":11280,"name":"QWsin","slogan":"","badge":null,"isAdmin":false,"isBanned":false,"color":"Gray","ccfLevel":0,"background":""},{"uid":3925,"name":"TMXi","slogan":null,"badge":null,"isAdmin":false,"isBanned":false,"color":"Gray","ccfLevel":0,"background":""},{"uid":26937,"name":"_soul_","slogan":"CSP 2019 RP++","badge":null,"isAdmin":false,"isBanned":false,"color":"Gray","ccfLevel":0,"background":""}]}